neurocombat_sklearn/__init__.py
neurocombat_sklearn/_version.py
neurocombat_sklearn/neurocombat_sklearn.py
neurocombat_sklearn/tests/__init__.py
neurocombat_sklearn/tests/test_common.py
neurocombat_sklearn-0.1.3.dist-info/LICENSE
neurocombat_sklearn-0.1.3.dist-info/METADATA
neurocombat_sklearn-0.1.3.dist-info/WHEEL
neurocombat_sklearn-0.1.3.dist-info/top_level.txt
neurocombat_sklearn-0.1.3.dist-info/RECORD
