Metadata-Version: 2.1
Name: neurocombat-sklearn
Version: 0.1.3
Summary: Harmonizing neuroimaging data across sites. Implementation of neurocombat using sklearn format
Home-page: https://github.com/Warvito/neurocombat-sklearn
Author: Walter Hugo Lopez Pinaya
License: UNKNOWN
Project-URL: Source Code, https://github.com/Warvito/neurocombat-sklearn
Platform: UNKNOWN
Classifier: Programming Language :: Python :: 3
Classifier: License :: OSI Approved :: MIT License
Classifier: Operating System :: OS Independent
Requires-Dist: scikit-learn
